Workbook

Sheet Assumptions
A1: SAHULATKAAR — 5-YEAR MODEL ASSUMPTIONS
A2: Blue cells are inputs — change any of them and the entire model recalculates.
A4: PRICING (Rs / month)
A5: Chhota plan | B5: 2500
A6: Dukaan plan | B6: 5000
A7: Karobaar plan | B7: 12000
A8: Plan mix — Chhota | B8: 0.3
A9: Plan mix — Dukaan | B9: 0.55
A10: Plan mix — Karobaar | B10: 0.15
A11: Blended ARPU (Rs/mo) | B11: =SUMPRODUCT(B5:B7,B8:B10)
A12: Annual price increase (from Y2) | B12: 0.08
A13: Setup fee per new merchant (one-time) | B13: 5000
A15: GROWTH | C15: Y1 | D15: Y2 | E15: Y3 | F15: Y4 | G15: Y5
A16: New merchants signed / month | C16: 15 | D16: 45 | E16: 110 | F16: 220 | G16: 400 | H16: Field sales + digital; PK has ~500k WhatsApp-selling retailers
A17: Monthly churn | B17: 0.03
A19: DIRECT COST PER ACTIVE MERCHANT (Rs / month)
A20: AI (Gemini) usage | B20: 350
A21: Hosting & infrastructure | B21: 120
A22: WhatsApp / BSP fees | B22: 800 | H22: Blended: BSP early, Meta Tech Provider at scale; customer-initiated msgs are free
A23: Total direct cost | B23: =SUM(B20:B22)
A25: TEAM | C25: Y1 | D25: Y2 | E25: Y3 | F25: Y4 | G25: Y5
A26: Engineers (headcount) | C26: 2 | D26: 3 | E26: 5 | F26: 8 | G26: 12
A27: Avg engineer salary (Rs/mo, Y1) | B27: 350000
A28: Merchants per support agent | B28: 150
A29: Support agent salary (Rs/mo, Y1) | B29: 70000
A30: Management cost (Rs/mo) | C30: 300000 | D30: 500000 | E30: 800000 | F30: 1200000 | G30: 1800000
A31: Salary inflation / yr | B31: 0.1
A33: SALES & MARKETING
A34: CAC per merchant (Rs) | B34: 8000
A35: Brand budget (Rs/yr) | C35: 1200000 | D35: 3000000 | E35: 6000000 | F35: 10000000 | G35: 15000000
A37: OTHER
A38: G&A / office (Rs/mo) | C38: 150000 | D38: 250000 | E38: 400000 | F38: 700000 | G38: 1000000
A39: Corporate tax rate | B39: 0.29
A40: PKR per USD | B40: 280

Sheet Monthly
A1: MONTHLY ENGINE — 60 months (all formulas; drives the annual Forecast)
A3: Month # | B3: 1 | C3: =B3+1 | D3: =C3+1 | E3: =D3+1 | F3: =E3+1 | G3: =F3+1 | H3: =G3+1 | I3: =H3+1 | J3: =I3+1 | ... BI3: =BH3+1
A4: Year | B4: =INT((B3-1)/12)+1 | C4: =INT((C3-1)/12)+1 | D4: =INT((D3-1)/12)+1 | E4: =INT((E3-1)/12)+1 | F4: =INT((F3-1)/12)+1 | G4: =INT((G3-1)/12)+1 | H4: =INT((H3-1)/12)+1 | I4: =INT((I3-1)/12)+1 | ... BI4: =INT((BI3-1)/12)+1
A5: Price escalator | B5: =(1+Assumptions!$B$12)^(B4-1) | C5: =(1+Assumptions!$B$12)^(C4-1) | D5: =(1+Assumptions!$B$12)^(D4-1) | E5: =(1+Assumptions!$B$12)^(E4-1) | F5: =(1+Assumptions!$B$12)^(F4-1) | G5: =(1+Assumptions!$B$12)^(G4-1) | H5: =(1+Assumptions!$B$12)^(H4-1) | I5: =(1+Assumptions!$B$12)^(I4-1) | ... BI5: =(1+Assumptions!$B$12)^(BI4-1)
A6: Blended ARPU (Rs/mo) | B6: =Assumptions!$B$11*B5 | C6: =Assumptions!$B$11*C5 | D6: =Assumptions!$B$11*D5 | E6: =Assumptions!$B$11*E5 | F6: =Assumptions!$B$11*F5 | G6: =Assumptions!$B$11*G5 | H6: =Assumptions!$B$11*H5 | I6: =Assumptions!$B$11*I5 | ... BI6: =Assumptions!$B$11*BI5
A7: Merchants — start | B7: 0 | C7: =B10 | D7: =C10 | E7: =D10 | F7: =E10 | G7: =F10 | H7: =G10 | I7: =H10 | J7: =I10 | ... BI7: =BH10
A8: New merchants | B8: =INDEX(Assumptions!$C$16:$G$16,1,B4) | C8: =INDEX(Assumptions!$C$16:$G$16,1,C4) | D8: =INDEX(Assumptions!$C$16:$G$16,1,D4) | E8: =INDEX(Assumptions!$C$16:$G$16,1,E4) | F8: =INDEX(Assumptions!$C$16:$G$16,1,F4) | G8: =INDEX(Assumptions!$C$16:$G$16,1,G4) | H8: =INDEX(Assumptions!$C$16:$G$16,1,H4) | I8: =INDEX(Assumptions!$C$16:$G$16,1,I4) | ... BI8: =INDEX(Assumptions!$C$16:$G$16,1,BI4)
A9: Churned | B9: =B7*Assumptions!$B$17 | C9: =C7*Assumptions!$B$17 | D9: =D7*Assumptions!$B$17 | E9: =E7*Assumptions!$B$17 | F9: =F7*Assumptions!$B$17 | G9: =G7*Assumptions!$B$17 | H9: =H7*Assumptions!$B$17 | I9: =I7*Assumptions!$B$17 | ... BI9: =BI7*Assumptions!$B$17
A10: Merchants — end | B10: =B7+B8-B9 | C10: =C7+C8-C9 | D10: =D7+D8-D9 | E10: =E7+E8-E9 | F10: =F7+F8-F9 | G10: =G7+G8-G9 | H10: =H7+H8-H9 | I10: =I7+I8-I9 | ... BI10: =BI7+BI8-BI9
A11: Average active | B11: =(B7+B10)/2 | C11: =(C7+C10)/2 | D11: =(D7+D10)/2 | E11: =(E7+E10)/2 | F11: =(F7+F10)/2 | G11: =(G7+G10)/2 | H11: =(H7+H10)/2 | I11: =(I7+I10)/2 | ... BI11: =(BI7+BI10)/2
A12: Subscription revenue (Rs) | B12: =B11*B6 | C12: =C11*C6 | D12: =D11*D6 | E12: =E11*E6 | F12: =F11*F6 | G12: =G11*G6 | H12: =H11*H6 | I12: =I11*I6 | ... BI12: =BI11*BI6
A13: Setup-fee revenue (Rs) | B13: =B8*Assumptions!$B$13 | C13: =C8*Assumptions!$B$13 | D13: =D8*Assumptions!$B$13 | E13: =E8*Assumptions!$B$13 | F13: =F8*Assumptions!$B$13 | G13: =G8*Assumptions!$B$13 | H13: =H8*Assumptions!$B$13 | I13: =I8*Assumptions!$B$13 | ... BI13: =BI8*Assumptions!$B$13
A14: Total revenue (Rs) | B14: =B12+B13 | C14: =C12+C13 | D14: =D12+D13 | E14: =E12+E13 | F14: =F12+F13 | G14: =G12+G13 | H14: =H12+H13 | I14: =I12+I13 | ... BI14: =BI12+BI13
A15: Direct costs (Rs) | B15: =B11*Assumptions!$B$23 | C15: =C11*Assumptions!$B$23 | D15: =D11*Assumptions!$B$23 | E15: =E11*Assumptions!$B$23 | F15: =F11*Assumptions!$B$23 | G15: =G11*Assumptions!$B$23 | H15: =H11*Assumptions!$B$23 | I15: =I11*Assumptions!$B$23 | ... BI15: =BI11*Assumptions!$B$23
A16: Gross profit (Rs) | B16: =B14-B15 | C16: =C14-C15 | D16: =D14-D15 | E16: =E14-E15 | F16: =F14-F15 | G16: =G14-G15 | H16: =H14-H15 | I16: =I14-I15 | ... BI16: =BI14-BI15

Sheet Forecast
A1: SAHULATKAAR — 5-YEAR FORECAST (Rs)
A2: Every figure is a formula driven by the Assumptions sheet. Simplified EBITDA model (no D&A/financing).
B3: Year 1 (FY27) | C3: Year 2 (FY28) | D3: Year 3 (FY29) | E3: Year 4 (FY30) | F3: Year 5 (FY31)
A4: Year index | B4: 1 | C4: 2 | D4: 3 | E4: 4 | F4: 5
A6: New merchants signed | B6: =SUMIF(Monthly!$B$4:$BI$4,B4,Monthly!$B$8:$BI$8) | C6: =SUMIF(Monthly!$B$4:$BI$4,C4,Monthly!$B$8:$BI$8) | D6: =SUMIF(Monthly!$B$4:$BI$4,D4,Monthly!$B$8:$BI$8) | E6: =SUMIF(Monthly!$B$4:$BI$4,E4,Monthly!$B$8:$BI$8) | F6: =SUMIF(Monthly!$B$4:$BI$4,F4,Monthly!$B$8:$BI$8)
A7: Merchants — end of year | B7: =INDEX(Monthly!$B$10:$BI$10,1,B4*12) | C7: =INDEX(Monthly!$B$10:$BI$10,1,C4*12) | D7: =INDEX(Monthly!$B$10:$BI$10,1,D4*12) | E7: =INDEX(Monthly!$B$10:$BI$10,1,E4*12) | F7: =INDEX(Monthly!$B$10:$BI$10,1,F4*12)
A8: Average active merchants | B8: =AVERAGEIF(Monthly!$B$4:$BI$4,B4,Monthly!$B$11:$BI$11) | C8: =AVERAGEIF(Monthly!$B$4:$BI$4,C4,Monthly!$B$11:$BI$11) | D8: =AVERAGEIF(Monthly!$B$4:$BI$4,D4,Monthly!$B$11:$BI$11) | E8: =AVERAGEIF(Monthly!$B$4:$BI$4,E4,Monthly!$B$11:$BI$11) | F8: =AVERAGEIF(Monthly!$B$4:$BI$4,F4,Monthly!$B$11:$BI$11)
A10: Subscription revenue | B10: =SUMIF(Monthly!$B$4:$BI$4,B4,Monthly!$B$12:$BI$12) | C10: =SUMIF(Monthly!$B$4:$BI$4,C4,Monthly!$B$12:$BI$12) | D10: =SUMIF(Monthly!$B$4:$BI$4,D4,Monthly!$B$12:$BI$12) | E10: =SUMIF(Monthly!$B$4:$BI$4,E4,Monthly!$B$12:$BI$12) | F10: =SUMIF(Monthly!$B$4:$BI$4,F4,Monthly!$B$12:$BI$12)
A11: Setup-fee revenue | B11: =SUMIF(Monthly!$B$4:$BI$4,B4,Monthly!$B$13:$BI$13) | C11: =SUMIF(Monthly!$B$4:$BI$4,C4,Monthly!$B$13:$BI$13) | D11: =SUMIF(Monthly!$B$4:$BI$4,D4,Monthly!$B$13:$BI$13) | E11: =SUMIF(Monthly!$B$4:$BI$4,E4,Monthly!$B$13:$BI$13) | F11: =SUMIF(Monthly!$B$4:$BI$4,F4,Monthly!$B$13:$BI$13)
A12: Total revenue | B12: =B10+B11 | C12: =C10+C11 | D12: =D10+D11 | E12: =E10+E11 | F12: =F10+F11
A13: Direct costs (AI + hosting + WhatsApp) | B13: =SUMIF(Monthly!$B$4:$BI$4,B4,Monthly!$B$15:$BI$15) | C13: =SUMIF(Monthly!$B$4:$BI$4,C4,Monthly!$B$15:$BI$15) | D13: =SUMIF(Monthly!$B$4:$BI$4,D4,Monthly!$B$15:$BI$15) | E13: =SUMIF(Monthly!$B$4:$BI$4,E4,Monthly!$B$15:$BI$15) | F13: =SUMIF(Monthly!$B$4:$BI$4,F4,Monthly!$B$15:$BI$15)
A14: Gross profit | B14: =B12-B13 | C14: =C12-C13 | D14: =D12-D13 | E14: =E12-E13 | F14: =F12-F13
A15: Gross margin | B15: =B14/B12 | C15: =C14/C12 | D15: =D14/D12 | E15: =E14/E12 | F15: =F14/F12
A17: OPERATING EXPENSES
A18: Engineering | B18: =INDEX(Assumptions!$C$26:$G$26,1,B4)*Assumptions!$B$27*12*(1+Assumptions!$B$31)^(B4-1) | C18: =INDEX(Assumptions!$C$26:$G$26,1,C4)*Assumptions!$B$27*12*(1+Assumptions!$B$31)^(C4-1) | D18: =INDEX(Assumptions!$C$26:$G$26,1,D4)*Assumptions!$B$27*12*(1+Assumptions!$B$31)^(D4-1) | E18: =INDEX(Assumptions!$C$26:$G$26,1,E4)*Assumptions!$B$27*12*(1+Assumptions!$B$31)^(E4-1) | F18: =INDEX(Assumptions!$C$26:$G$26,1,F4)*Assumptions!$B$27*12*(1+Assumptions!$B$31)^(F4-1)
A19: Customer support | B19: =ROUNDUP(B7/Assumptions!$B$28,0)*Assumptions!$B$29*12*(1+Assumptions!$B$31)^(B4-1) | C19: =ROUNDUP(C7/Assumptions!$B$28,0)*Assumptions!$B$29*12*(1+Assumptions!$B$31)^(C4-1) | D19: =ROUNDUP(D7/Assumptions!$B$28,0)*Assumptions!$B$29*12*(1+Assumptions!$B$31)^(D4-1) | E19: =ROUNDUP(E7/Assumptions!$B$28,0)*Assumptions!$B$29*12*(1+Assumptions!$B$31)^(E4-1) | F19: =ROUNDUP(F7/Assumptions!$B$28,0)*Assumptions!$B$29*12*(1+Assumptions!$B$31)^(F4-1)
A20: Management | B20: =INDEX(Assumptions!$C$30:$G$30,1,B4)*12 | C20: =INDEX(Assumptions!$C$30:$G$30,1,C4)*12 | D20: =INDEX(Assumptions!$C$30:$G$30,1,D4)*12 | E20: =INDEX(Assumptions!$C$30:$G$30,1,E4)*12 | F20: =INDEX(Assumptions!$C$30:$G$30,1,F4)*12
A21: Sales & marketing (CAC × new + brand) | B21: =B6*Assumptions!$B$34+INDEX(Assumptions!$C$35:$G$35,1,B4) | C21: =C6*Assumptions!$B$34+INDEX(Assumptions!$C$35:$G$35,1,C4) | D21: =D6*Assumptions!$B$34+INDEX(Assumptions!$C$35:$G$35,1,D4) | E21: =E6*Assumptions!$B$34+INDEX(Assumptions!$C$35:$G$35,1,E4) | F21: =F6*Assumptions!$B$34+INDEX(Assumptions!$C$35:$G$35,1,F4)
A22: G&A / office | B22: =INDEX(Assumptions!$C$38:$G$38,1,B4)*12 | C22: =INDEX(Assumptions!$C$38:$G$38,1,C4)*12 | D22: =INDEX(Assumptions!$C$38:$G$38,1,D4)*12 | E22: =INDEX(Assumptions!$C$38:$G$38,1,E4)*12 | F22: =INDEX(Assumptions!$C$38:$G$38,1,F4)*12
A23: Total opex | B23: =SUM(B18:B22) | C23: =SUM(C18:C22) | D23: =SUM(D18:D22) | E23: =SUM(E18:E22) | F23: =SUM(F18:F22)
A25: EBITDA | B25: =B14-B23 | C25: =C14-C23 | D25: =D14-D23 | E25: =E14-E23 | F25: =F14-F23
A26: EBITDA margin | B26: =IF(B12=0,0,B25/B12) | C26: =IF(C12=0,0,C25/C12) | D26: =IF(D12=0,0,D25/D12) | E26: =IF(E12=0,0,E25/E12) | F26: =IF(F12=0,0,F25/F12)
A27: Tax (on positive EBITDA) | B27: =MAX(0,B25)*Assumptions!$B$39 | C27: =MAX(0,C25)*Assumptions!$B$39 | D27: =MAX(0,D25)*Assumptions!$B$39 | E27: =MAX(0,E25)*Assumptions!$B$39 | F27: =MAX(0,F25)*Assumptions!$B$39
A28: Net result | B28: =B25-B27 | C28: =C25-C27 | D28: =D25-D27 | E28: =E25-E27 | F28: =F25-F27
A29: Cumulative net cash | B29: =B28 | C29: =B29+C28 | D29: =C29+D28 | E29: =D29+E28 | F29: =E29+F28
A31: IN USD
A32: Revenue (USD) | B32: =B12/Assumptions!$B$40 | C32: =C12/Assumptions!$B$40 | D32: =D12/Assumptions!$B$40 | E32: =E12/Assumptions!$B$40 | F32: =F12/Assumptions!$B$40
A33: EBITDA (USD) | B33: =B25/Assumptions!$B$40 | C33: =C25/Assumptions!$B$40 | D33: =D25/Assumptions!$B$40 | E33: =E25/Assumptions!$B$40 | F33: =F25/Assumptions!$B$40
A35: ARR run-rate at year end | B35: =INDEX(Monthly!$B$10:$BI$10,1,B4*12)*INDEX(Monthly!$B$6:$BI$6,1,B4*12)*12 | C35: =INDEX(Monthly!$B$10:$BI$10,1,C4*12)*INDEX(Monthly!$B$6:$BI$6,1,C4*12)*12 | D35: =INDEX(Monthly!$B$10:$BI$10,1,D4*12)*INDEX(Monthly!$B$6:$BI$6,1,D4*12)*12 | E35: =INDEX(Monthly!$B$10:$BI$10,1,E4*12)*INDEX(Monthly!$B$6:$BI$6,1,E4*12)*12 | F35: =INDEX(Monthly!$B$10:$BI$10,1,F4*12)*INDEX(Monthly!$B$6:$BI$6,1,F4*12)*12
A37: UNIT ECONOMICS
A38: LTV (ARPU × GM ÷ churn) | B38: =Assumptions!B11*Forecast!B15/Assumptions!B17
A39: LTV / CAC | B39: =B38/Assumptions!B34
A40: CAC payback (months) | B40: =Assumptions!B34/(Assumptions!B11*Forecast!B15)

Sheet Dashboard
A1: SAHULATKAAR — INVESTOR DASHBOARD
A3: Merchants (Year 5) | B3: Revenue Year 5 | C3: Revenue Year 5 (USD) | D3: EBITDA margin Year 5 | E3: Gross margin | F3: LTV / CAC | G3: CAC payback (months)
A4: =Forecast!F7 | B4: =Forecast!F12 | C4: =Forecast!F32 | D4: =Forecast!F26 | E4: =Forecast!F15 | F4: =Forecast!B39 | G4: =Forecast!B40
